py3mschap/U32.py
py3mschap/__init__.py
py3mschap/des.py
py3mschap/des_c.py
py3mschap/des_data.py
py3mschap/md4.py
py3mschap/mppe.py
py3mschap/mschap.py
py3mschap/utils.py
py3mschap-0.2.post1.dist-info/LICENSE
py3mschap-0.2.post1.dist-info/METADATA
py3mschap-0.2.post1.dist-info/WHEEL
py3mschap-0.2.post1.dist-info/top_level.txt
py3mschap-0.2.post1.dist-info/RECORD
