Metadata-Version: 2.1
Name: py3mschap
Version: 0.2.post1
Summary: python3 mschap module
Home-page: https://github.com/astibal/py3mschap
Author: Ales Stibal
Author-email: astib@mag0.net
License: LGPL
Keywords: mschap,mschapv1,mschapv2,py3mschap
Platform: UNKNOWN
Classifier: Development Status :: 4 - Beta
Classifier: Intended Audience :: Developers
Classifier: Programming Language :: Python :: 3.6
Classifier: Topic :: Software Development :: Libraries :: Python Modules
